isa_model/__init__.py
isa_model/core/model_manager.py
isa_model/core/model_registry.py
isa_model/core/model_router.py
isa_model/core/model_storage.py
isa_model/core/model_version.py
isa_model/core/resource_manager.py
isa_model/core/storage/hf_storage.py
isa_model/core/storage/local_storage.py
isa_model/core/storage/minio_storage.py
isa_model/deployment/gpu_fp16_ds8/models/deepseek_r1/1/model.py
isa_model/deployment/gpu_fp16_ds8/scripts/download_model.py
isa_model/deployment/gpu_int8_ds8/app/server.py
isa_model/deployment/gpu_int8_ds8/scripts/test_client.py
isa_model/deployment/gpu_int8_ds8/scripts/test_client_os.py
isa_model/eval/__init__.py
isa_model/eval/benchmarks.py
isa_model/eval/factory.py
isa_model/eval/metrics.py
isa_model/inference/__init__.py
isa_model/inference/ai_factory.py
isa_model/inference/ai_factory_original.py
isa_model/inference/base.py
isa_model/inference/adapter/unified_api.py
isa_model/inference/providers/__init__.py
isa_model/inference/providers/base_provider.py
isa_model/inference/providers/model_cache_manager.py
isa_model/inference/providers/ollama_provider.py
isa_model/inference/providers/openai_provider.py
isa_model/inference/providers/replicate_provider.py
isa_model/inference/providers/triton_provider.py
isa_model/inference/services/__init__.py
isa_model/inference/services/base_service.py
isa_model/inference/services/audio/base_stt_service.py
isa_model/inference/services/audio/base_tts_service.py
isa_model/inference/services/audio/openai_tts_service.py
isa_model/inference/services/embedding/base_embed_service.py
isa_model/inference/services/embedding/ollama_embed_service.py
isa_model/inference/services/embedding/openai_embed_service.py
isa_model/inference/services/llm/__init__.py
isa_model/inference/services/llm/base_llm_service.py
isa_model/inference/services/llm/ollama_llm_service.py
isa_model/inference/services/llm/openai_llm_service.py
isa_model/inference/services/others/table_transformer_service.py
isa_model_sdk-0.0.1.dist-info/licenses/LICENSE
isa_model_sdk-0.0.1.dist-info/METADATA
isa_model_sdk-0.0.1.dist-info/WHEEL
isa_model_sdk-0.0.1.dist-info/top_level.txt
isa_model_sdk-0.0.1.dist-info/RECORD
