Metadata-Version: 2.4
Name: isa_model_sdk
Version: 0.0.1
Summary: Unified AI model serving framework
Author: isA_Model Contributors
Classifier: Development Status :: 3 - Alpha
Classifier: Intended Audience :: Developers
Classifier: Operating System :: OS Independent
Classifier: Programming Language :: Python :: 3
Requires-Python: >=3.8
License-File: LICENSE
Requires-Dist: fastapi>=0.95.0
Requires-Dist: numpy>=1.20.0
Requires-Dist: httpx>=0.23.0
Requires-Dist: pydantic>=2.0.0
Requires-Dist: uvicorn>=0.22.0
Requires-Dist: requests>=2.28.0
Requires-Dist: aiohttp>=3.8.0
Requires-Dist: transformers>=4.30.0
Requires-Dist: langchain-core>=0.1.0
Requires-Dist: huggingface-hub>=0.16.0
Requires-Dist: kubernetes>=25.3.0
Requires-Dist: mlflow>=2.4.0
Requires-Dist: torch>=2.0.0
Requires-Dist: openai>=1.10.0
Requires-Dist: replicate>=0.23.0
Requires-Dist: python-dotenv>=1.0.0
Requires-Dist: ollama>=0.3.0
Requires-Dist: runpod>=1.0.0
Requires-Dist: boto3>=1.26.0
Requires-Dist: google-cloud-storage>=2.7.0
Requires-Dist: datasets>=2.10.0
Requires-Dist: accelerate>=0.20.0
Requires-Dist: bitsandbytes>=0.39.0
Requires-Dist: peft>=0.4.0
Requires-Dist: trl>=0.4.0
Dynamic: license-file
